{
  "title": "Página de Aterrizaje 5 | Memorae",
  "description": "Experimenta nuestro quinto diseño con enrutamiento automático de idioma y detección de zona horaria.",
  "keywords": "página de aterrizaje, diseño, multiidioma, l5, memorae",
  "ogTitle": "Página de Aterrizaje 5 | Memorae",
  "ogDescription": "Descubre nuestra quinta página con detección inteligente de idioma.",
  "twitterTitle": "Página de Aterrizaje 5 | Memorae",
  "twitterDescription": "Mira nuestro diseño innovador.",
  "locale": "es_ES",
  "lang": "es"
}
